GCD_LCM/__init__.py
GCD_LCM-0.0.3.dist-info/LICENCE.txt
GCD_LCM-0.0.3.dist-info/METADATA
GCD_LCM-0.0.3.dist-info/WHEEL
GCD_LCM-0.0.3.dist-info/top_level.txt
GCD_LCM-0.0.3.dist-info/RECORD
